fmetools/__init__.py
fmetools/_deprecated.py
fmetools/features.py
fmetools/guiparams.py
fmetools/http.py
fmetools/localize.py
fmetools/logfile.py
fmetools/paramparsing.py
fmetools/parsers.py
fmetools/plugins.py
fmetools/scripted_selection.py
fmetools/utils.py
fmetools/webservices.py
fmetools-0.13.1.dist-info/licenses/LICENSE
fmetools-0.13.1.dist-info/METADATA
fmetools-0.13.1.dist-info/WHEEL
fmetools-0.13.1.dist-info/top_level.txt
fmetools-0.13.1.dist-info/RECORD
