Metadata-Version: 2.4
Name: fmetools
Version: 0.13.1
Summary: Tools for extending Safe Software's FME using Python.
Home-page: https://github.com/safesoftware/fmetools
Author: Safe Software Inc.
License: BSD
Project-URL: Documentation, https://docs.safe.com/fme/html/fmetools/
Keywords: FME fmeobjects
Classifier: Programming Language :: Python :: 3
Classifier: License :: OSI Approved :: BSD License
Classifier: Intended Audience :: Developers
Requires-Python: >=3.8
License-File: LICENSE
Provides-Extra: dev
Requires-Dist: build>=1.2.2; extra == "dev"
Requires-Dist: pytest>=8.3.5; extra == "dev"
Requires-Dist: pytest-cov>=5.0.0; extra == "dev"
Requires-Dist: pytest-recording>=0.13.2; extra == "dev"
Requires-Dist: hypothesis>=6.113.0; extra == "dev"
Requires-Dist: ruff>=0.14.4; extra == "dev"
Dynamic: license-file
